{
  "alonso": "alo_oficial",
  "vettel": "sebvettelnews",
  "tsunoda": "yukitsunoda07",
  "stroll": "lance_stroll",
  "latifi": "NicholasLatifi",
  "russell": "GeorgeRussell63",
  "raikkonen": "Kimi7iceman",
  "giovinazzi": "Anto_Giovinazzi",
  "mick_schumacher": "SchumacherMick",
  "mazepin": "nikita_mazepin",
  "hamilton": "LewisHamilton",
  "max_verstappen": "Max33Verstappen",
  "norris": "LandoNorris",
  "bottas": "ValtteriBottas",
  "perez": "SChecoPerez",
  "sainz": "Carlossainz55",
  "leclerc": "Charles_Leclerc",
  "gasly": "PierreGASLY",
  "ricciardo": "danielricciardo",
  "ocon": "OconEsteban"
}
